# Java 类型擦除深度分析

## 什么是类型擦除？

类型擦除(Type Erasure) 是 Java 泛型实现的核心机制。为了保持与旧版本 Java 的兼容性，Java 编译器会在编译时将泛型类型信息移除，在字节码中用原始类型(raw type)替代。这意味着运行时无法获得完整的泛型类型信息。

## 核心演示代码

### RuntimeTypeBypassDemo.java - 类型擦除漏洞演示

```java
package com.example;

import java.util.*;
import java.lang.reflect.Method;

public class RuntimeTypeBypassDemo {
    public static void main(String[] args) throws Exception {
        List<String> stringList = new ArrayList<>();
        stringList.add("hello");
        
        // 编译时会报错，所以我们用反射绕过
        System.out.println("=== Using Reflection to Bypass Compile-time Check ===");
        
        // 获取 add 方法
        Method addMethod = List.class.getMethod("add", Object.class);
        
        // 运行时添加 Integer 到 String list - 成功！
        boolean result = (Boolean) addMethod.invoke(stringList, 42);
        System.out.println("Successfully added integer 42: " + result);
        
        // 打印列表内容
        System.out.println("List contents: " + stringList);
        System.out.println("List size: " + stringList.size());
        
        // 遍历时才会出错
        System.out.println("=== Iterating through list ===");
        try {
            for (String s : stringList) {  // 这里会 ClassCastException
                System.out.println("String: " + s);
            }
        } catch (ClassCastException e) {
            System.out.println("ClassCastException caught: " + e.getMessage());
            System.out.println("Error occurred when trying to cast Integer to String");
        }
        
        // 直接获取对象不会出错
        System.out.println("=== Direct access ===");
        Object obj = stringList.get(1);
        System.out.println("Object at index 1: " + obj + " (type: " + obj.getClass() + ")");
    }
}
```

### GenericClassDemo.java - 泛型类演示

```java
package com.example;

import java.util.List;
import java.util.ArrayList;

public class GenericClassDemo<T extends Number> {
    private List<T> items;
    
    public GenericClassDemo() {
        this.items = new ArrayList<>();
    }
    
    public void addItem(T item) {
        items.add(item);
    }
    
    public List<T> getItems() {
        return items;
    }
    
    public <E> void processWithGenericMethod(E element, List<? super E> sink) {
        sink.add(element);
    }
}
```

## 字节码分析

### 1. 方法签名的类型擦除

在 RuntimeTypeBypassDemo 的字节码中，我们可以看到泛型类型如何被擦除：

```bytecode
206: invokeinterface #12, 2  // InterfaceMethod java/util/List.add:(Ljava/lang/Object;)Z
```

注意这里的方法签名是 `add:(Ljava/lang/Object;)Z`，而不是 `add:(Ljava/lang/String;)Z`。这说明编译器已经将泛型参数 `String` 擦除为了原始类型 `Object`。

### 2. 强制类型转换的自动插入

当我们从泛型容器中取出元素时，编译器会自动插入类型转换指令：

```bytecode
138: invokeinterface #87, 1  // InterfaceMethod java/util/Iterator.next:()Ljava/lang/Object;
143: checkcast     #62       // class java/lang/String
146: astore        5
```

`next()` 方法返回 `Object`，编译器插入了 `checkcast` 指令将其转换为 `String`。这就是 `ClassCastException` 发生的位置。

### 3. 异常处理表

字节码中的异常处理表明确标识了 ClassCastException 的捕获范围：

```bytecode
Exception table:
   from    to  target type
     118   164   167   Class java/lang/ClassCastException
```

### 4. 本地变量表中的类型信息

有趣的是，在本地变量表的类型表(LocalVariableTypeTable)中，我们仍然可以看到泛型类型信息：

```bytecode
LocalVariableTable:
  Start  Length  Slot  Name   Signature
      8     227     1 stringList   Ljava/util/List;

LocalVariableTypeTable:
  Start  Length  Slot  Name   Signature
      8     227     1 stringList   Ljava/util/List<Ljava/lang/String;>;
```

## 类型擦除的补偿机制

虽然运行时泛型信息大部分被擦除，但 Java 确实提供了一些补偿机制来保留部分泛型信息：

### 1. Signature 属性

在字节码中，类、方法和字段都保留完整的泛型签名信息。从 GenericClassDemo 的字节码可以看到：

```bytecode
// 类级别的签名
Signature: #25  // <T:Ljava/lang/Number;>Ljava/lang/Object;

// 方法签名 - addItem(T item)
Signature: #18  // (TT;)V

// 方法签名 - getItems()
Signature: #21  // ()Ljava/util/List<TT;>;

// 泛型方法签名 - processWithGenericMethod
Signature: #24  // <E:Ljava/lang/Object;>(TE;Ljava/util/List<-TE;>;)V
```

这些 Signature 属性包含了完整的泛型类型信息，包括：
- 类型参数 (`<T:Ljava/lang/Number;>`)
- 边界约束 (`T extends Number`)
- 通配符 (`? super E` 表示为 `-TE`)

### 2. LocalVariableTypeTable (调试信息)

当使用 `-g` 编译选项时，编译器会生成 LocalVariableTypeTable：

```bytecode
LocalVariableTypeTable:
  Start  Length  Slot  Name   Signature
      8     227     1 stringList   Ljava/util/List<Ljava/lang/String;>;
      0      16     0  this   Lcom/example/GenericClassDemo<TT;>;
      0      12     1  item   TT;
```

**重要提醒**: 这个表仅在启用调试信息时存在（`javac -g`），在生产环境的 release 版本中通常被移除。

### 3. 反射 API 的能力与限制演示

```java
package com.example;

import java.lang.reflect.*;
import java.util.List;

public class GenericReflectionTest {
    public static void main(String[] args) throws Exception {
        Class<GenericClassDemo> clazz = GenericClassDemo.class;
        
        System.out.println("=== Class Level Generic Info ===");
        TypeVariable<?>[] typeParameters = clazz.getTypeParameters();
        for (TypeVariable<?> typeParam : typeParameters) {
            System.out.println("Type Parameter: " + typeParam.getName());
            Type[] bounds = typeParam.getBounds();
            for (Type bound : bounds) {
                System.out.println("  Bound: " + bound.getTypeName());
            }
        }
        
        System.out.println("\n=== Field Generic Info ===");
        Field itemsField = clazz.getDeclaredField("items");
        Type fieldType = itemsField.getGenericType();
        System.out.println("Field type: " + fieldType);
        if (fieldType instanceof ParameterizedType) {
            ParameterizedType pType = (ParameterizedType) fieldType;
            Type[] actualTypes = pType.getActualTypeArguments();
            System.out.println("  Actual type argument: " + actualTypes[0]);
        }
        
        System.out.println("\n=== Method Generic Info ===");
        Method addMethod = clazz.getMethod("addItem", Number.class);
        Type[] paramTypes = addMethod.getGenericParameterTypes();
        System.out.println("addItem parameter type: " + paramTypes[0]);
        
        System.out.println("\n=== Runtime Instance Type Info ===");
        GenericClassDemo<Integer> instance = new GenericClassDemo<>();
        // Note: Cannot get actual type parameter Integer here due to type erasure!
        System.out.println("Instance class: " + instance.getClass());
        System.out.println("Instance type parameter: Cannot retrieve (type erasure)");
    }
}
```

**运行输出**:
```
=== Class Level Generic Info ===
Type Parameter: T
  Bound: java.lang.Number

=== Field Generic Info ===
Field type: java.util.List<T>
  Actual type argument: T

=== Method Generic Info ===
addItem parameter type: T

=== Runtime Instance Type Info ===
Instance class: class com.example.GenericClassDemo
Instance type parameter: Cannot retrieve (type erasure)
```

**关键洞察**：
- **可以获取的信息**: 类声明时的类型参数、方法签名中的泛型信息
- **无法获取的信息**: 运行时实例的具体类型参数（如 `GenericClassDemo<Integer>` 中的 `Integer`）

## 类型擦除的核心影响

### 1. 运行时类型检查绕过

示例代码展示了如何通过反射绕过编译时的类型检查：

```java
Method addMethod = List.class.getMethod("add", Object.class);
boolean result = (Boolean) addMethod.invoke(stringList, 42);
```

由于类型擦除，`List.add()` 方法的实际签名是 `add(Object)`，所以反射调用可以成功添加任意类型的对象。

### 2. 延迟的类型错误

错误不会在添加时发生，而是在类型转换时：

- 添加 `Integer` 到 `List<String>` → 成功
- 遍历时自动转换 `Integer` 为 `String` → `ClassCastException`

### 3. 直接访问不会触发转换

```java
Object obj = stringList.get(1);  // 不会抛出异常
```

当我们直接获取 `Object` 类型时，字节码中没有 `checkcast` 指令，因此不会发生运行时类型检查。

## 编译对比：有无调试信息的差异

### 标准编译 (`javac` 默认)
保留 Signature 属性和 LocalVariableTypeTable。

### 无调试信息编译 (`javac -g:none`)
- 移除 LocalVariableTypeTable
- 保留 Signature 属性
- 移除行号表等调试信息

这说明 **Signature 属性是类型擦除的核心补偿机制**，而 LocalVariableTypeTable 主要用于调试。

## 实际影响和最佳实践

### 问题
- 运行时无法进行完整的泛型类型检查
- 通过反射可以绕过泛型约束
- 类型安全仅在编译时保证

### 最佳实践
1. **避免原始类型**: 始终指定泛型参数，避免使用 `List` 而不是 `List<T>`
2. **谨慎使用反射**: 在操作泛型集合时要格外小心
3. **TypeToken 模式**: 在需要运行时类型信息时，考虑使用 TypeToken 模式
4. **全面测试**: 编写单元测试覆盖类型边界情况
5. **静态分析工具**: 使用 IDE 和静态分析工具检测潜在的类型安全问题

## 总结

Java 的类型擦除是一个设计权衡的结果：它保持了向后兼容性，但牺牲了运行时的类型安全性。通过字节码分析，我们可以清楚地看到：

1. **核心机制**: 编译器移除类型参数，用原始类型替代，插入必要的类型转换
2. **补偿机制**: Signature 属性保留完整的泛型声明信息，反射可以访问这些信息
3. **根本限制**: 无法获取运行时实例的具体类型参数

理解这些机制对于编写健壮的 Java 代码至关重要，特别是在使用反射、序列化或与遗留代码交互时。类型擦除解释了 Java 泛型的各种"奇怪"行为，也为我们在实际开发中避免相关陷阱提供了理论基础。

## Kotlin Reified 类型参数：突破类型擦除

### 什么是 Reified 类型参数？

Kotlin 提供了 `reified` 类型参数来部分解决 JVM 类型擦除的问题。通过 `inline` + `reified` 的组合，Kotlin 可以在运行时保留类型信息。

### 核心机制演示

```kotlin
// Kotlin reified 函数
inline fun <reified T> isInstance(obj: Any): Boolean {
    return obj is T  // 可以直接使用 T 进行类型检查
}

// 调用
val result = isInstance<String>("hello")  // 编译时展开
```

### 字节码分析：内联展开的真相

**关键发现**: Reified 的"魔法"实际上是编译时的内联展开：

```bytecode
// 调用 isInstance<String>("hello") 的字节码
47: ldc           #46    // class java/lang/String  <- 具体类型！
49: invokestatic  #52    // getOrCreateKotlinClass
...
56: instanceof    #46    // class java/lang/String  <- 直接类型检查！
```

**核心洞察**:
- 编译器在每个调用点将 `T` 替换为具体类型
- `instanceof String` 而非 `instanceof Object`
- 没有类型擦除的痕迹

### 标准库中的 Reified 函数

Kotlin 标准库大量使用 reified 来提供类型安全的 API：

```kotlin
// 这些调用都会进行编译时类型替换
val stringArray = arrayOf<String>()      // 生成: anewarray String
val emptyIntArray = emptyArray<Int>()    // 生成: anewarray Integer
val strings = mixedList.filterIsInstance<String>()  // 生成具体类型检查
```

**字节码证据**:
```bytecode
374: anewarray     #29   // class java/lang/String  <- arrayOf<String>()
377: anewarray     #90   // class java/lang/Integer <- arrayOf<Int>()
```

## 跨语言类型系统对比分析

### Java vs Kotlin：根本差异

| 方面 | Java | Kotlin |
|------|------|--------|
| **类型擦除** | 完全擦除，运行时无法获取 | Reified 可保留类型信息 |
| **实现机制** | 编译器插入 checkcast | 编译时内联展开 |
| **运行时检查** | 延迟到类型转换 | 可直接进行类型检查 |
| **API 设计** | 需要传递 Class 参数 | 直接使用类型参数 |

### 跨 JAR 调用的惊人真相

**实验发现**: Kotlin 标准库中的 reified 函数可以正常跨 JAR 调用！

```kotlin
// 调用标准库中的 reified 函数
val stringType = typeOf<String>()           // 正常工作
val stringArray = arrayOf<String>()         // 正常工作
val strings = list.filterIsInstance<String>() // 正常工作
```

**原因分析**:
- Kotlin 编译器内置了对标准库 reified 函数的支持
- 无需访问源码，编译器就知道如何展开这些函数
- 编译时直接生成具体类型的字节码

### Java 调用 Kotlin Reified 的限制

**实验结果**: Java 无法调用真正的 reified 函数

```java
// 编译错误：找不到符号 kotlin.ArraysKt
Object[] array = kotlin.ArraysKt.arrayOf("hello", "world");
```

**但可以调用非 reified 版本**:
```java
// 正常工作：调用 vararg 版本，不是 reified 版本
List<String> list = CollectionsKt.listOf("hello", "world");
```

**根本原因**:
1. Java 编译器不理解 Kotlin 的 `inline` 语义
2. 真正的 reified 函数在 Java 中不可见
3. Kotlin 为互操作性提供了非 reified 的替代版本

## 实际开发中的影响和限制

### Reified 的优势

1. **类型安全**: 编译时类型检查，运行时保留类型信息
2. **API 简洁**: 无需传递 Class 参数
3. **性能优越**: 编译时优化，没有反射开销

### Reified 的限制

1. **必须是 inline 函数**: 限制了使用场景
2. **编译时确定**: 无法用于运行时动态类型
3. **Java 互操作**: Java 无法调用真正的 reified 函数
4. **代码膨胀**: 每个调用点都会展开，增加字节码大小

### 设计模式对比

**Java TypeToken 模式**:
```java
// 需要显式传递类型信息
public <T> T fromJson(String json, Class<T> clazz) {
    return gson.fromJson(json, clazz);
}
```

**Kotlin Reified 模式**:
```kotlin
// 类型信息自动保留
inline fun <reified T> fromJson(json: String): T {
    return gson.fromJson(json, T::class.java)
}
```

## 深度技术洞察

### 编译器的角色差异

**Java 编译器**:
- 被动擦除类型信息
- 依赖运行时的 checkcast 指令
- 类型安全仅在编译时保证

**Kotlin 编译器**:
- 主动进行内联展开
- 编译时生成具体类型的代码
- 在字节码层面实现类型具体化

### JVM 层面的统一性

虽然语言机制不同，但最终都运行在同一个 JVM 上：

```bytecode
// Java: 编译器生成的 checkcast
143: checkcast     #62    // class java/lang/String

// Kotlin: 编译器生成的直接类型检查  
56: instanceof     #46    // class java/lang/String
```

两种方式都生成了具体的类型指令，但 Kotlin 的方式更直接、更高效。

### 未来发展方向

**Project Valhalla** (Java 未来特性) 可能会改变这一切：
- 真正的泛型特化 (Generic Specialization)
- 值类型和原始类型的泛型支持
- 可能减少 Kotlin reified 的独特优势

## 第三方库 Reified 函数的深度分析

### 关键发现：第三方库 Reified 函数同样支持内联展开

通过测试 Jackson Kotlin 模块的 `readValue<T>()` 函数，我们发现了一个重要事实：**第三方库的 reified 函数与标准库一样，也能被 Kotlin 编译器正确内联展开**。

### 实验代码与结果

```kotlin
// 第三方库 reified 函数调用
val mapper = jacksonObjectMapper()
val person: Person = mapper.readValue<Person>(personJson)    // 成功！
val company: Company = mapper.readValue<Company>(companyJson) // 成功！
val employees: List<Person> = mapper.readValue<List<Person>>(employeesJson) // 复杂泛型也成功！
```

**运行结果**：
```
Jackson reified readValue<Person>: Person(name=Alice, age=30)
Jackson reified readValue<Company>: Company(name=TechCorp, employees=[...])
Jackson reified readValue<List<Person>>: [Person(name=Dave, age=28), ...]
Jackson reified readValue<Map<String, Person>>: {key1=Person(name=Frank, age=27), ...}
```

### 字节码分析：内联展开的证据

**关键发现**：编译器为每个 reified 调用生成了专门的内联类：

```
ThirdPartyReifiedTestKt$testJacksonReifiedFunctions$$inlined$readValue$1.class
ThirdPartyReifiedTestKt$testJacksonReifiedFunctions$$inlined$readValue$2.class
ThirdPartyReifiedTestKt$testJacksonReifiedFunctions$$inlined$readValue$3.class
ThirdPartyReifiedTestKt$testJacksonReifiedFunctions$$inlined$readValue$4.class
```

**内联类分析**：
```java
public final class ThirdPartyReifiedTestKt$testJacksonReifiedFunctions$$inlined$readValue$1 
    extends com.fasterxml.jackson.core.type.TypeReference<com.example.Person> {
    
    // 编译时生成的具体类型参数：Person
    // Signature: Lcom/fasterxml/jackson/core/type/TypeReference<Lcom/example/Person;>;
}
```

### 核心机制对比

| 方面 | 标准库 Reified | 第三方库 Reified |
|------|----------------|------------------|
| **编译时处理** | 直接类型替换 (`anewarray String`) | 生成内联 TypeReference 类 |
| **字节码生成** | 具体类型指令 | 调用 + 类型检查指令 |
| **实现方式** | 内联函数体展开 | 内联 + 匿名类生成 |
| **跨 JAR 工作** | ✅ 编译器内置支持 | ✅ 通过源码内联实现 |

### 第三方库 Reified 的字节码模式

**调用模式**：
```bytecode
// 1. 生成具体的 TypeReference 子类
203: new           #104  // class ...$$inlined$readValue$1
206: dup
207: invokespecial #105  // Method "init":()V
210: checkcast     #52   // class TypeReference

// 2. 调用实际的 Jackson 方法
213: invokevirtual #58   // Method readValue:(String;TypeReference;)Object;

// 3. 运行时类型检查和转换
222: aload         8
224: instanceof    #60   // class com/example/Person
227: ifne          321   // 跳转到成功路径
324: checkcast     #60   // class com/example/Person
```

### 重要洞察

#### 1. **第三方库 Reified 的工作原理**
- **不是魔法**：第三方库 reified 函数必须是 `inline` 函数
- **源码内联**：Kotlin 编译器访问第三方库的源码，在编译时展开函数体
- **类型具体化**：为每个类型参数生成专门的匿名类（如 `TypeReference<Person>`）

#### 2. **与标准库的根本差异**
- **标准库**：编译器有特殊内置支持，直接生成优化的字节码
- **第三方库**：通过标准的内联机制 + 泛型捕获实现，更符合 JVM 语义

#### 3. **实际限制**
- **源码可见性**：第三方库必须提供源码或者编译器能访问的内联信息
- **编译时依赖**：需要在编译时包含第三方库的完整依赖
- **Java 不可调用**：Java 代码仍然无法调用真正的 reified 函数

### 实用价值

这个发现表明 **Kotlin 的 reified 生态系统比预想的更加完整**：

1. **库开发者**可以提供 reified API 来改善用户体验
2. **应用开发者**可以享受一致的 reified 体验，无论是标准库还是第三方库
3. **编译器优化**使得第三方 reified 函数与标准库具有相似的性能特征

**结论**: Kotlin 的 reified 类型参数通过编译时技巧巧妙地绕过了 JVM 类型擦除的限制，为开发者提供了更好的类型安全和 API 体验，但也带来了一定的使用限制和互操作性问题。这种设计充分展示了编译器创新对语言表达力的重要影响。

## 第三方库 "Reified" 函数的终极揭秘

### 核心问题：编译时魔法的背后机制

当我们调用第三方库（如 Jackson Kotlin 模块）中的 `readValue<Person>(json)` 时，Kotlin 编译器是如何知道这是一个需要内联的 reified 函数的？JAR 文件中究竟存储了什么信息？

**突破性发现**：第三方库的 "reified" 函数实现了一个巧妙的**编译器协作协议**，该协议完全符合 JVM 和字节码标准，但为 Kotlin 编译器提供了执行内联和类型具体化所需的所有信息。

### 第三方库 Reified 的"一体两面"架构

借鉴 Gemini 的分析框架，第三方库中的 inline reified 函数在编译后会产生两个截然不同的产物：

#### 1. **方法存根（Method Stub）**：为 Java 调用者准备的后备方案

**目标**：维持 JVM 二进制兼容性，为不理解 Kotlin 元数据的调用者提供优雅失败机制。

**实现特征**：
```java
// 字节码中实际存在的方法存根
public static final synthetic Object readValue(ObjectMapper $this, String content) {
    Intrinsics.needClassReification(); // 立即抛出异常
    throw new UnsupportedOperationException("This function has a reified type parameter and thus can only be inlined");
}
```

#### 2. **元数据函数体（Inlinable Body）**：为 Kotlin 编译器准备的内联蓝图

**目标**：存储完整的函数体逻辑，供其他 Kotlin 编译器读取和内联展开。

**存储位置**：`@kotlin.Metadata` 注解中的序列化数据

**关键占位符**：`reifiedOperationMarker(id, typeParameterIdentifier)`

```kotlin
// 存储在 @Metadata 中的逻辑（简化表示）
inline fun <reified T> ObjectMapper.readValue(content: String): T {
    val typeRef = object : TypeReference<T>() {}  // reified 调用
    val result = readValue(content, typeRef)
    
    // 编译器占位符：在内联时替换为具体类型检查
    reifiedOperationMarker(3, "T")  // id=3表示instanceof检查
    return result as T
}
```

### JVM 标准兼容的四层协作机制

**核心洞察**：这些机制都是对 JVM 现有特性的创造性运用，而非对 JVM 的扩展或破坏。

| 层级 | 机制 | JVM 合规性 | 具体作用 |
|------|------|-----------|---------|
| **注解层** | `@kotlin.Metadata` | ✅ 标准注解机制（JLS §9.7） | 存储 Kotlin 特有信息，对 JVM 不透明 |
| **方法层** | `ACC_SYNTHETIC` | ✅ JVM 规范 §4.1 访问标志 | 标记编译器生成的特殊方法 |
| **调用层** | `needClassReification()` | ✅ 标准静态方法调用 | 运行时失败回退，编译时标记识别 |
| **操作层** | `reifiedOperationMarker()` | ✅ 标准方法调用 | 编译时占位符，运行时永不执行 |

### 编译器识别和处理流程

**步骤拆解**：如何从 JAR 文件到类型具体化

1. **库扫描阶段**
   ```
   Kotlin编译器 → 扫描classpath中的.jar文件
   ↓
   发现@kotlin.Metadata注解 → "这是Kotlin编译的代码"
   ```

2. **方法分析阶段**
   ```
   发现ACC_SYNTHETIC方法 → "这个方法需要特殊处理"
   ↓
   解析@Metadata中的函数体数据 → 获取完整的内联蓝图
   ```

3. **标记识别阶段**
   ```
   在元数据中找到reifiedOperationMarker调用
   ↓
   识别类型操作点和参数信息
   ```

4. **内联展开阶段**
   ```
   调用点：mapper.readValue<Person>(json)
   ↓
   替换T为Person，生成具体的TypeReference<Person>子类
   ↓
   将reifiedOperationMarker替换为 instanceof Person 指令
   ```

### 字节码证据：占位符的替换过程

**元数据中的占位符**：
```bytecode
// @Metadata中存储的"指令"（永不实际执行）
invokestatic kotlin/jvm/internal/Intrinsics.reifiedOperationMarker:(ILjava/lang/String;)V
    参数1 (I): 3  // 操作类型：3=instanceof检查
    参数2 (String): "T"  // 类型参数标识符
```

**内联后的实际代码**：
```bytecode
// 编译器生成的具体类型检查
203: new           #104  // class ...$$inlined$readValue$1 (extends TypeReference<Person>)
...
222: aload         8
224: instanceof    #60   // class com/example/Person  ← 具体类型！
227: ifne          321
324: checkcast     #60   // class com/example/Person  ← 具体转换！
```

### 调用路径对比：Java vs Kotlin

**Kotlin 调用 Kotlin**：
```
mapper.readValue<Person>(json)
↓
Kotlin编译器忽略字节码中的方法存根
↓
读取@kotlin.Metadata中的函数体表示
↓
发现reifiedOperationMarker标记点
↓
执行内联，生成TypeReference<Person>子类
↓
替换marker为 instanceof Person 指令
↓
成功完成类型具体化
```

**Java 调用 Kotlin**：
```
// Java代码无法直接调用reified函数
mapper.readValue(json, Person.class)  // 必须显式传递Class
↓
Java编译器不认识@kotlin.Metadata
↓
链接到字节码中的ACC_SYNTHETIC方法存根
↓
生成标准的INVOKESTATIC指令
↓
运行时JVM执行方法存根
↓
调用needClassReification()
↓
抛出UnsupportedOperationException
```

### 与标准库 Reified 的本质差异

| 对比维度 | 标准库 Reified | 第三方库 "Reified" |
|---------|----------------|-------------------|
| **编译器支持** | 内置硬编码支持 | 通用标记识别机制 |
| **字节码模式** | 直接类型指令 (`anewarray String`) | 内联类生成 (`TypeReference<T>`) |
| **工作原理** | 编译器特殊处理 | 占位符替换协议 |
| **跨JAR实现** | 编译器内置逻辑 | 元数据 + 标记系统 |
| **JVM兼容性** | ✅ 完全兼容 | ✅ 完全兼容（更巧妙） |
| **Java互操作** | ❌ 不可调用 | ❌ 同样不可调用 |

### 邮政系统类比：编译器协作的直观理解

借用 Gemini 的精彩比喻来理解这套机制：

**JVM 就像邮政系统**：
- `ACC_SYNTHETIC`：官方的"机密文件"印章，所有邮递员都认识
- `needClassReification()`：寄送一个普通包裹，邮政系统只负责投递，不关心内容
- `@kotlin.Metadata`：标准信封，但里面装的是用Kotlin"密码"写成的信

**编译器协作过程**：
1. **库编译器**（发件人）用Kotlin密码写信，装入标准信封
2. **邮政系统**（JVM）负责投递，但看不懂密码内容
3. **应用编译器**（收件人）拿到信封，用Kotlin密码本解读
4. **Java调用者**（不懂密码的人）只能触发包裹中的"炸弹"（异常）

### 技术哲学：标准框架内的创新

这套机制体现了优秀的工程设计原则：

1. **约束中的创新**：在严格的JVM标准约束下实现高级语言特性
2. **渐进式兼容**：新特性不破坏现有生态，优雅降级
3. **工具链友好**：利用标准机制，不需要定制JVM
4. **用户体验优先**：隐藏复杂性，提供简洁统一的API

**结论**：第三方库"reified"函数的实现是编译器设计的杰作，它证明了在现有平台约束内实现突破性语言特性的可能性，为其他JVM语言的类型系统创新提供了宝贵的设计模式。